[
  {
    "filename": "Kindergarten-1-End-of-Unit-Assessment-teacher-guide-.pdf",
    "grade": "GK",
    "unit": "U1",
    "section": null,
    "assessment_number": 1,
    "question_number": 1,
    "image": "images/GK_U1/GK_U1_a1_q1.png",
    "image_width": 1700,
    "image_height": 884,
    "source_pages": [
      1
    ]
  },
  {
    "filename": "Kindergarten-1-End-of-Unit-Assessment-teacher-guide-.pdf",
    "grade": "GK",
    "unit": "U1",
    "section": null,
    "assessment_number": 1,
    "question_number": 2,
    "image": "images/GK_U1/GK_U1_a1_q2.png",
    "image_width": 1700,
    "image_height": 1167,
    "source_pages": [
      1,
      2
    ]
  },
  {
    "filename": "Kindergarten-1-End-of-Unit-Assessment-teacher-guide-.pdf",
    "grade": "GK",
    "unit": "U1",
    "section": null,
    "assessment_number": 1,
    "question_number": 3,
    "image": "images/GK_U1/GK_U1_a1_q3.png",
    "image_width": 1700,
    "image_height": 939,
    "source_pages": [
      2
    ]
  },
  {
    "filename": "Kindergarten-1-End-of-Unit-Assessment-teacher-guide-.pdf",
    "grade": "GK",
    "unit": "U1",
    "section": null,
    "assessment_number": 1,
    "question_number": 4,
    "image": "images/GK_U1/GK_U1_a1_q4.png",
    "image_width": 1700,
    "image_height": 4372,
    "source_pages": [
      2,
      3,
      4
    ]
  }
]